chatspatial/__init__.py
chatspatial/__main__.py
chatspatial/config.py
chatspatial/server.py
chatspatial/spatial_mcp_adapter.py
chatspatial/cli/__init__.py
chatspatial/models/__init__.py
chatspatial/models/analysis.py
chatspatial/models/data.py
chatspatial/tools/__init__.py
chatspatial/tools/annotation.py
chatspatial/tools/cell_communication.py
chatspatial/tools/cnv_analysis.py
chatspatial/tools/condition_comparison.py
chatspatial/tools/differential.py
chatspatial/tools/embeddings.py
chatspatial/tools/enrichment.py
chatspatial/tools/integration.py
chatspatial/tools/preprocessing.py
chatspatial/tools/spatial_domains.py
chatspatial/tools/spatial_genes.py
chatspatial/tools/spatial_registration.py
chatspatial/tools/spatial_statistics.py
chatspatial/tools/trajectory.py
chatspatial/tools/velocity.py
chatspatial/tools/deconvolution/__init__.py
chatspatial/tools/deconvolution/base.py
chatspatial/tools/deconvolution/card.py
chatspatial/tools/deconvolution/cell2location.py
chatspatial/tools/deconvolution/destvi.py
chatspatial/tools/deconvolution/flashdeconv.py
chatspatial/tools/deconvolution/rctd.py
chatspatial/tools/deconvolution/spotlight.py
chatspatial/tools/deconvolution/stereoscope.py
chatspatial/tools/deconvolution/tangram.py
chatspatial/tools/visualization/__init__.py
chatspatial/tools/visualization/cell_comm.py
chatspatial/tools/visualization/cnv.py
chatspatial/tools/visualization/core.py
chatspatial/tools/visualization/deconvolution.py
chatspatial/tools/visualization/enrichment.py
chatspatial/tools/visualization/expression.py
chatspatial/tools/visualization/feature.py
chatspatial/tools/visualization/integration.py
chatspatial/tools/visualization/main.py
chatspatial/tools/visualization/multi_gene.py
chatspatial/tools/visualization/spatial_stats.py
chatspatial/tools/visualization/trajectory.py
chatspatial/tools/visualization/velocity.py
chatspatial/utils/__init__.py
chatspatial/utils/adata_utils.py
chatspatial/utils/compat.py
chatspatial/utils/compute.py
chatspatial-1.1.2.dist-info/licenses/LICENSE
chatspatial-1.1.2.dist-info/METADATA
chatspatial-1.1.2.dist-info/WHEEL
chatspatial-1.1.2.dist-info/entry_points.txt
chatspatial-1.1.2.dist-info/top_level.txt
chatspatial-1.1.2.dist-info/RECORD
