Metadata-Version: 2.4
Name: chatspatial
Version: 1.1.2
Summary: ChatSpatial: Natural language-driven spatial transcriptomics analysis via Model Context Protocol (MCP) integration
Author-email: Chen Yang <cafferychen777@tamu.edu>
License: MIT
Project-URL: Homepage, https://github.com/cafferychen777/ChatSpatial
Project-URL: Documentation, https://chatspatial.readthedocs.io
Project-URL: Repository, https://github.com/cafferychen777/ChatSpatial
Project-URL: Issues, https://github.com/cafferychen777/ChatSpatial/issues
Keywords: spatial-transcriptomics,single-cell,mcp,llm,bioinformatics,scanpy,squidpy
Classifier: Development Status :: 4 - Beta
Classifier: Intended Audience :: Science/Research
Classifier: License :: OSI Approved :: MIT License
Classifier: Operating System :: OS Independent
Classifier: Programming Language :: Python :: 3
Classifier: Programming Language :: Python :: 3.11
Classifier: Programming Language :: Python :: 3.12
Classifier: Programming Language :: Python :: 3.13
Classifier: Topic :: Scientific/Engineering :: Bio-Informatics
Requires-Python: <3.14,>=3.11
License-File: LICENSE
Requires-Dist: mcp>=1.17.0
Requires-Dist: numpy>=1.21.0
Requires-Dist: pandas>=1.3.0
Requires-Dist: scipy>=1.7.0
Requires-Dist: scikit-learn>=1.0.0
Requires-Dist: matplotlib>=3.5.0
Requires-Dist: seaborn>=0.11.0
Requires-Dist: Pillow>=8.0.0
Requires-Dist: scanpy<2.0,>=1.9.0
Requires-Dist: anndata>=0.11.0
Requires-Dist: squidpy>=1.2.0
Requires-Dist: umap-learn>=0.5.0
Requires-Dist: igraph>=0.9.0
Requires-Dist: leidenalg>=0.8.0
Requires-Dist: pydantic<3.0,>=2.0.0
Requires-Dist: click>=8.0.0
Requires-Dist: aiohttp>=3.8.0
Requires-Dist: jinja2>=3.0.0
Requires-Dist: scvi-tools<2.0,>=1.0.0
Requires-Dist: mudata>=0.2.0
Requires-Dist: scvelo>=0.2.5
Requires-Dist: liana
Requires-Dist: cellphonedb<6.0,>=5.0.0
Requires-Dist: fastccc>=0.1.0
Requires-Dist: harmonypy>=0.0.9
Requires-Dist: bbknn>=1.5.0
Requires-Dist: esda>=2.4.0
Requires-Dist: libpysal>=4.6.0
Requires-Dist: gseapy>=1.0.0
Requires-Dist: flashdeconv>=0.1.0
Provides-Extra: full
Requires-Dist: torch<3.0,>=2.0.0; extra == "full"
Requires-Dist: SpaGCN<2.0,>=1.2.5; extra == "full"
Requires-Dist: GraphST>=1.1.0; extra == "full"
Requires-Dist: cell2location>=0.1.4; extra == "full"
Requires-Dist: cellrank<3.0,>=2.0.0; extra == "full"
Requires-Dist: palantir>=1.0.0; extra == "full"
Requires-Dist: petsc4py<4.0,>=3.18.0; sys_platform != "win32" and extra == "full"
Requires-Dist: slepc4py<4.0,>=3.18.0; sys_platform != "win32" and extra == "full"
Requires-Dist: scanorama>=1.7.0; extra == "full"
Requires-Dist: spatialde>=1.1.3; extra == "full"
Requires-Dist: scikit-misc>=0.5.0; extra == "full"
Requires-Dist: tangram-sc>=1.0.0; extra == "full"
Requires-Dist: singler>=0.4.0; sys_platform != "win32" and extra == "full"
Requires-Dist: singlecellexperiment>=0.4.0; sys_platform != "win32" and extra == "full"
Requires-Dist: celldex>=0.3.0; sys_platform != "win32" and extra == "full"
Requires-Dist: mllmcelltype>=0.1.0; extra == "full"
Requires-Dist: rpy2<3.7,>=3.5.0; extra == "full"
Requires-Dist: anndata2ri>=1.3.0; extra == "full"
Requires-Dist: pysal>=2.6.0; extra == "full"
Requires-Dist: statsmodels>=0.13.0; extra == "full"
Requires-Dist: networkx>=2.6.0; extra == "full"
Requires-Dist: POT>=0.9.0; extra == "full"
Requires-Dist: paste-bio>=1.0.0; extra == "full"
Requires-Dist: infercnvpy>=0.4.0; extra == "full"
Requires-Dist: pydeseq2>=0.4.0; extra == "full"
Requires-Dist: enrichmap; extra == "full"
Requires-Dist: statannotations>=0.2.0; extra == "full"
Requires-Dist: pygam>=0.8.0; extra == "full"
Requires-Dist: scikit-gstat>=1.0.0; extra == "full"
Requires-Dist: adjustText>=0.8.0; extra == "full"
Requires-Dist: splot>=1.1.0; extra == "full"
Requires-Dist: spatialdata>=0.2.0; extra == "full"
Provides-Extra: dev
Requires-Dist: pytest>=8.0.0; extra == "dev"
Requires-Dist: pytest-asyncio<2.0,>=0.23.0; extra == "dev"
Requires-Dist: black<26.0,>=22.0.0; extra == "dev"
Requires-Dist: mypy<2.0,>=1.0.0; extra == "dev"
Requires-Dist: ruff>=0.1.0; extra == "dev"
Requires-Dist: isort>=5.0.0; extra == "dev"
Requires-Dist: pre-commit<5.0,>=3.0.0; extra == "dev"
Dynamic: license-file
